microwave_controller/display_7_segmentos/Decoder.v
module Display7seg (BCDin, BINout);
	input [3:0] BCDin;
	output reg [6:0] BINout;

	initial begin
		BINout =  7'b111_1111;
	end
	
	always @* begin
		//active_low inputs
		/*
		design:

			  ___g___
			 |		 |
			b|		 |f
			 |___a___|
			 |		 |
			c|		 |e
			 |_______|
			 	 d
		*/
		case (BCDin)
			//              abc_defg
			4'b0000: BINout = 7'b100_0000;
			4'b0001: BINout = 7'b111_1001;
			4'b0010: BINout = 7'b010_0100;
			4'b0011: BINout = 7'b011_0000;
			4'b0100: BINout = 7'b001_1001;
			4'b0101: BINout = 7'b001_0010;
			4'b0110: BINout = 7'b000_0010;
			4'b0111: BINout = 7'b111_1000;
			4'b1000: BINout = 7'b000_0000;
			4'b1001: BINout = 7'b001_0000;
			default: BINout = 7'b111_1111;
		endcase
	end
endmodule

microwave_controller/display_7_segmentos/testbenchs/Decoder_tb.v
`timescale 1ns/1ps
`include "..\Decoder.v"

module Decoder_tb;

    reg [3:0] BCDin_tb;
    wire [6:0] BINout_tb;

    Display7seg uut(BCDin_tb, BINout_tb);

    initial begin
        $dumpfile("../wave_forms/Decoder.vcd");
        $dumpvars(0, Decoder_tb);

        BCDin_tb = 4'd7; #10;
        BCDin_tb = 4'd3; #10;
        BCDin_tb = 4'd9; #10;
        BCDin_tb = 4'd1; #10;
        BCDin_tb = 4'b0000; #10;
        BCDin_tb = 4'bxxxx; #10;
        BCDin_tb = 4'bzzzz; #10;
        BCDin_tb = 4'd4; #10;
        BCDin_tb = 4'd2; #10;
    end

endmodule

microwave_controller/display_7_segmentos/wave_forms/Decoder.vcd
$date
	Mon May 09 00:28:43 2022
$end
$version
	Icarus Verilog
$end
$timescale
	1ps
$end
$scope module Decoder_tb $end
$var wire 7 ! BINout_tb [6:0] $end
$var reg 4 " BCDin_tb [3:0] $end
$scope module uut $end
$var wire 4 # BCDin [3:0] $end
$var reg 7 $ BINout [6:0] $end
$upscope $end
$upscope $end
$enddefinitions $end
#0
$dumpvars
b1111000 $
b111 #
b111 "
b1111000 !
$end
#10000
b110000 !
b110000 $
b11 "
b11 #
#20000
b10000 !
b10000 $
b1001 "
b1001 #
#30000
b1111001 !
b1111001 $
b1 "
b1 #
#40000
b1000000 !
b1000000 $
b0 "
b0 #
#50000
b1111111 !
b1111111 $
bx "
bx #
#60000
bz "
bz #
#70000
b11001 !
b11001 $
b100 "
b100 #
#80000
b100100 !
b100100 $
b10 "
b10 #
