microwave_controller/counter/counter10.v
module counter10 (enable, clk, data, rstn, loadn, count, tc, zero);

    input [3:0] data;
    input clk, rstn, loadn, enable;

    output reg [3:0] count;
    output wire tc, zero;

    assign tc = (count == 4'd0) ? 1'b1 : 1'b0;
    assign zero = tc;

    always @(posedge clk, negedge rstn) begin
        // reset (clear) em nivel baixo (entrada assíncrona)
        if (~rstn) begin
            count <= 4'd0;
        end else begin
            // enable nivel alto
            if (enable) begin
                // contagem decrescente (mod 10)
                if (count == 4'd0) begin
                    count <= 4'd9;
                end else begin
                    count <= count - 4'd1;
                end

            end else if (~loadn) begin
                count <= data;
            end
        end
    end

endmodule

microwave_controller/counter/testbenchs/counter10_tb.v
`timescale 1ms/1ns
`include "..\counter10.v"

module counter10_tb;

    reg [3:0] data_tb;
    reg clk_tb, rstn_tb, loadn_tb, enable_tb;

    wire [3:0] count_tb;
    wire tc_tb, zero_tb;

    counter10 uut(enable_tb, clk_tb, data_tb, rstn_tb, loadn_tb, count_tb, tc_tb, zero_tb);

    initial begin
        $dumpfile("../wave_forms/counter10.vcd");
        $dumpvars(0, counter10_tb);

        data_tb = 4'd0; clk_tb = 1'b0; rstn_tb = 1'b1; loadn_tb = 1'b1; enable_tb = 1'b0;
    end

    initial begin
        repeat(500)
            #5 clk_tb = ~clk_tb; 
    end

    initial begin
        // recebe os inputs
        #10 data_tb = 4'd4;
        #40 loadn_tb = 1'b0;
        #50 loadn_tb = 1'b1;

        #100 data_tb = 4'd2;
        #50 loadn_tb = 1'b0;
        #50 loadn_tb = 1'b1;

        // tenta dar um clear
        #10 rstn_tb = 1'b0;
        #10 rstn_tb = 1'b1;

        #100 data_tb = 4'd8;
        #50 loadn_tb = 1'b0;
        #50 loadn_tb = 1'b1;

        // ativa a contagem
        #10 enable_tb = 1'b1;

        // tenta dar um load enquanto conta
        #90 data_tb = 4'd5;
        #10 loadn_tb = 1'b0;
        #50 loadn_tb = 1'b1;

        // tenta dar um clear enquanto conta (força o nable para zero)
        #150 rstn_tb = 1'b0; enable_tb = 1'b0;
        #50 rstn_tb = 1'b1;
        #30;
    end

endmodule

microwave_controller/counter/wave_forms/counter10.vcd
$date
	Sun May 08 19:59:24 2022
$end
$version
	Icarus Verilog
$end
$timescale
	1ns
$end
$scope module counter10_tb $end
$var wire 1 ! zero_tb $end
$var wire 1 " tc_tb $end
$var wire 4 # count_tb [3:0] $end
$var reg 1 $ clk_tb $end
$var reg 4 % data_tb [3:0] $end
$var reg 1 & enable_tb $end
$var reg 1 ' loadn_tb $end
$var reg 1 ( rstn_tb $end
$scope module uut $end
$var wire 1 $ clk $end
$var wire 4 ) data [3:0] $end
$var wire 1 & enable $end
$var wire 1 ' loadn $end
$var wire 1 ( rstn $end
$var wire 1 ! zero $end
$var wire 1 " tc $end
$var reg 4 * count [3:0] $end
$upscope $end
$upscope $end
$enddefinitions $end
#0
$dumpvars
bx *
b0 )
1(
1'
0&
b0 %
0$
bx #
x"
x!
$end
#5000000
1$
#10000000
0$
b100 %
b100 )
#15000000
1$
#20000000
0$
#25000000
1$
#30000000
0$
#35000000
1$
#40000000
0$
#45000000
1$
#50000000
0$
0'
#55000000
0!
0"
b100 #
b100 *
1$
#60000000
0$
#65000000
1$
#70000000
0$
#75000000
1$
#80000000
0$
#85000000
1$
#90000000
0$
#95000000
1$
#100000000
0$
1'
#105000000
1$
#110000000
0$
#115000000
1$
#120000000
0$
#125000000
1$
#130000000
0$
#135000000
1$
#140000000
0$
#145000000
1$
#150000000
0$
#155000000
1$
#160000000
0$
#165000000
1$
#170000000
0$
#175000000
1$
#180000000
0$
#185000000
1$
#190000000
0$
#195000000
1$
#200000000
0$
b10 %
b10 )
#205000000
1$
#210000000
0$
#215000000
1$
#220000000
0$
#225000000
1$
#230000000
0$
#235000000
1$
#240000000
0$
#245000000
1$
#250000000
0$
0'
#255000000
b10 #
b10 *
1$
#260000000
0$
#265000000
1$
#270000000
0$
#275000000
1$
#280000000
0$
#285000000
1$
#290000000
0$
#295000000
1$
#300000000
0$
1'
#305000000
1$
#310000000
1!
1"
b0 #
b0 *
0$
0(
#315000000
1$
#320000000
0$
1(
#325000000
1$
#330000000
0$
#335000000
1$
#340000000
0$
#345000000
1$
#350000000
0$
#355000000
1$
#360000000
0$
#365000000
1$
#370000000
0$
#375000000
1$
#380000000
0$
#385000000
1$
#390000000
0$
#395000000
1$
#400000000
0$
#405000000
1$
#410000000
0$
#415000000
1$
#420000000
0$
b1000 %
b1000 )
#425000000
1$
#430000000
0$
#435000000
1$
#440000000
0$
#445000000
1$
#450000000
0$
#455000000
1$
#460000000
0$
#465000000
1$
#470000000
0$
0'
#475000000
0!
0"
b1000 #
b1000 *
1$
#480000000
0$
#485000000
1$
#490000000
0$
#495000000
1$
#500000000
0$
#505000000
1$
#510000000
0$
#515000000
1$
#520000000
0$
1'
#525000000
1$
#530000000
0$
1&
#535000000
b111 #
b111 *
1$
#540000000
0$
#545000000
b110 #
b110 *
1$
#550000000
0$
#555000000
b101 #
b101 *
1$
#560000000
0$
#565000000
b100 #
b100 *
1$
#570000000
0$
#575000000
b11 #
b11 *
1$
#580000000
0$
#585000000
b10 #
b10 *
1$
#590000000
0$
#595000000
b1 #
b1 *
1$
#600000000
0$
#605000000
1!
1"
b0 #
b0 *
1$
#610000000
0$
#615000000
0!
0"
b1001 #
b1001 *
1$
#620000000
0$
b101 %
b101 )
#625000000
b1000 #
b1000 *
1$
#630000000
0$
0'
#635000000
b111 #
b111 *
1$
#640000000
0$
#645000000
b110 #
b110 *
1$
#650000000
0$
#655000000
b101 #
b101 *
1$
#660000000
0$
#665000000
b100 #
b100 *
1$
#670000000
0$
#675000000
b11 #
b11 *
1$
#680000000
0$
1'
#685000000
b10 #
b10 *
1$
#690000000
0$
#695000000
b1 #
b1 *
1$
#700000000
0$
#705000000
1!
1"
b0 #
b0 *
1$
#710000000
0$
#715000000
0!
0"
b1001 #
b1001 *
1$
#720000000
0$
#725000000
b1000 #
b1000 *
1$
#730000000
0$
#735000000
b111 #
b111 *
1$
#740000000
0$
#745000000
b110 #
b110 *
1$
#750000000
0$
#755000000
b101 #
b101 *
1$
#760000000
0$
#765000000
b100 #
b100 *
1$
#770000000
0$
#775000000
b11 #
b11 *
1$
#780000000
0$
#785000000
b10 #
b10 *
1$
#790000000
0$
#795000000
b1 #
b1 *
1$
#800000000
0$
#805000000
1!
1"
b0 #
b0 *
1$
#810000000
0$
#815000000
0!
0"
b1001 #
b1001 *
1$
#820000000
0$
#825000000
b1000 #
b1000 *
1$
#830000000
1!
1"
b0 #
b0 *
0$
0&
0(
#835000000
1$
#840000000
0$
#845000000
1$
#850000000
0$
#855000000
1$
#860000000
0$
#865000000
1$
#870000000
0$
#875000000
1$
#880000000
0$
1(
