microwave_controller/counter/counter10.v
module counter10 (enable, clk, data, rstn, loadn, count, tc, zero);

    input [3:0] data;
    input clk, rstn, loadn, enable;

    output reg [3:0] count;
    output wire tc, zero;

    assign tc = (count == 4'd0) ? 1'b1 : 1'b0;
    assign zero = tc;

    always @(posedge clk, negedge rstn) begin
        // reset (clear) em nivel baixo (entrada assíncrona)
        if (~rstn) begin
            count <= 4'd0;
        end else begin
            // enable nivel alto
            if (enable) begin
                // contagem decrescente (mod 10)
                if (count == 4'd0) begin
                    count <= 4'd9;
                end else begin
                    count <= count - 4'd1;
                end

            end else if (~loadn) begin
                count <= data;
            end
        end
    end

endmodule

microwave_controller/counter/counter6.v
module counter6 (enable, clk, data, rstn, loadn, count, tc, zero);

    input [3:0] data;
    input clk, rstn, loadn, enable;

    output reg [3:0] count;
    output wire tc, zero;

    assign tc = (data == 4'd0 && count == 4'd0) ? 1'b1 : 1'b0;
    assign zero = (count == 4'd0) ? 1'b1 : 1'b0;

    always @(posedge clk, negedge rstn) begin
        // reset (clear) em nivel baixo (entrada assíncrona)
        if (~rstn) begin
            count <= 4'd0;
        end else begin
            // enable nivel alto
            if (enable) begin
                // contagem decrescente (mod 6)
                if (count == 4'd0) begin
                    count <= 4'd5;
                end else begin
                    count <= count - 4'd1;
                end

            end else if (~loadn) begin
                count <= data;
            end
        end
    end

endmodule

microwave_controller/counter/counter_level2.v
`include "./counter/counter10.v"
`include "./counter/counter6.v"

// manter apenas os nomes dos arquivos nos caminhos
// ao compilar no diretório ./microwave_controller/counter

module counter_level2(
    data, loadn, clrn, clk, enable,
    sec_ones_out, sec_tens_out, mins_out, zero
);

    input [3:0] data;
    input loadn, clrn, clk, enable;

    output reg [3:0] sec_ones_out, sec_tens_out, mins_out;
    output wire zero;

    wire [3:0] sec_ones, sec_tens, mins;
    wire tc_secones, tc_sectens, tc_mins, zero_secones, zero_sectens, zero_mins;

    counter10 sec_one(.enable(enable), .clk(clk), .data(data), .rstn(clrn), .loadn(loadn), .count(sec_ones), .tc(tc_secones), .zero(zero_secones));
    counter6 sec_ten(.enable(tc_secones & enable), .clk(clk), .data(sec_ones), .rstn(clrn), .loadn(loadn), .count(sec_tens), .tc(tc_sectens), .zero(zero_sectens));
    counter10 min(.enable(tc_sectens & enable), .clk(clk), .data(sec_tens), .rstn(clrn), .loadn(loadn), .count(mins), .tc(tc_mins), .zero(zero_mins));

    assign zero = zero_secones & zero_sectens & zero_mins;

    // remove zeros na esquerda e conta segundos maiores que 59 corretamente
    always @* begin
        sec_ones_out <= (sec_ones == 4'd0 && sec_tens == 4'd0 && mins == 4'd0) ? 4'bzzzz : sec_ones;

        if (~enable) begin
            mins_out <= (mins == 4'd0) ? 4'bzzzz : mins;
            sec_tens_out <= (sec_tens == 4'd0 && mins == 4'd0) ? 4'bzzzz : sec_tens;
        end else begin
            if (sec_tens > 4'd5) begin
                sec_tens_out <= sec_tens - 4'd6;
                mins_out <= mins + 4'd1;
            end else begin
                sec_tens_out <= (sec_tens == 4'd0 && mins == 4'd0) ? 4'bzzzz : sec_tens;
                mins_out <= (mins == 4'd0) ? 4'bzzzz : mins;
            end
        end
    end

endmodule

microwave_controller/counter/testbenchs/counter_level2_tb.v
`timescale 1ns/1ps
`include "counter_level2.v"

// este módulo deve ser compilado a partir do diretório "/microwave_controller/counter"
// devido à hierarquia de pastas
module counter_level2_tb;

    reg [3:0] data_tb;
    reg clk_tb, clrn_tb, loadn_tb, enable_tb;

    wire [3:0] sec_ones_tb, sec_tens_tb, mins_tb;
    wire zero_tb;

    counter_level2 uut(data_tb, loadn_tb, clrn_tb, clk_tb, enable_tb, sec_ones_tb, sec_tens_tb, mins_tb, zero_tb);

    initial begin
        $dumpfile("./wave_forms/counter_level2.vcd");
        $dumpvars(0, counter_level2_tb);

        data_tb = 4'd0; clk_tb = 1'b0; clrn_tb = 1'b1; loadn_tb = 1'b1; enable_tb = 1'b0;
    end

    initial begin
        #55 clk_tb = ~clk_tb;
        #50 clk_tb = ~clk_tb;

        #150 clk_tb = ~clk_tb;
        #50 clk_tb = ~clk_tb;

        #150 clk_tb = ~clk_tb;
        #50 clk_tb = ~clk_tb;

        #130 clk_tb = ~clk_tb;
        #50 clk_tb = ~clk_tb;

        #160 clk_tb = ~clk_tb;
        #50 clk_tb = ~clk_tb;

        #150 clk_tb = ~clk_tb;
        #50 clk_tb = ~clk_tb; #5;

        repeat(500) begin
            if (enable_tb) begin
                #5 clk_tb = ~clk_tb;
            end

            if (zero_tb) begin
                enable_tb = 0;
            end
        end
        
    end

    initial begin
        // recebe os inputs
        #10 data_tb = 4'd8;
        #40 loadn_tb = 1'b0;
        #50 loadn_tb = 1'b1; //100

        #100 data_tb = 4'd9;
        #50 loadn_tb = 1'b0;
        #50 loadn_tb = 1'b1; //300

        #100 data_tb = 4'd2;
        #50 loadn_tb = 1'b0;
        #50 loadn_tb = 1'b1; //500

        // tenta dar um clear
        #10 clrn_tb = 1'b0;
        #10 clrn_tb = 1'b1; //520

        // recebe os inputs de novo
        #70 data_tb = 4'd1;
        #40 loadn_tb = 1'b0;
        #50 loadn_tb = 1'b1; //690

        #100 data_tb = 4'd2;
        #50 loadn_tb = 1'b0;
        #50 loadn_tb = 1'b1; //890

        #100 data_tb = 4'd0;
        #50 loadn_tb = 1'b0;
        #50 loadn_tb = 1'b1; //1090

        // ativa a contagem
        #10 enable_tb = 1'b1; //1100

        // tenta dar um load enquanto conta (se o timer control funciona isso nunca acontece)
        #100 loadn_tb = 1'b1;
        #50 loadn_tb = 1'b1;

        // tenta dar um clear enquanto conta (força o enable para zero)
        #5000 clrn_tb = 1'b0; enable_tb = 1'b0;
        #50 clrn_tb = 1'b1;
        #30;
    end

endmodule

microwave_controller/counter/wave_forms/counter_level2.vcd
$date
	Mon May 09 00:37:59 2022
$end
$version
	Icarus Verilog
$end
$timescale
	1ps
$end
$scope module counter_level2_tb $end
$var wire 1 ! zero_tb $end
$var wire 4 " sec_tens_tb [3:0] $end
$var wire 4 # sec_ones_tb [3:0] $end
$var wire 4 $ mins_tb [3:0] $end
$var reg 1 % clk_tb $end
$var reg 1 & clrn_tb $end
$var reg 4 ' data_tb [3:0] $end
$var reg 1 ( enable_tb $end
$var reg 1 ) loadn_tb $end
$scope module uut $end
$var wire 1 % clk $end
$var wire 1 & clrn $end
$var wire 4 * data [3:0] $end
$var wire 1 ( enable $end
$var wire 1 ) loadn $end
$var wire 1 ! zero $end
$var wire 1 + zero_sectens $end
$var wire 1 , zero_secones $end
$var wire 1 - zero_mins $end
$var wire 1 . tc_sectens $end
$var wire 1 / tc_secones $end
$var wire 1 0 tc_mins $end
$var wire 4 1 sec_tens [3:0] $end
$var wire 4 2 sec_ones [3:0] $end
$var wire 4 3 mins [3:0] $end
$var reg 4 4 mins_out [3:0] $end
$var reg 4 5 sec_ones_out [3:0] $end
$var reg 4 6 sec_tens_out [3:0] $end
$scope module min $end
$var wire 1 % clk $end
$var wire 1 7 enable $end
$var wire 1 ) loadn $end
$var wire 1 & rstn $end
$var wire 1 - zero $end
$var wire 1 0 tc $end
$var wire 4 8 data [3:0] $end
$var reg 4 9 count [3:0] $end
$upscope $end
$scope module sec_one $end
$var wire 1 % clk $end
$var wire 4 : data [3:0] $end
$var wire 1 ( enable $end
$var wire 1 ) loadn $end
$var wire 1 & rstn $end
$var wire 1 , zero $end
$var wire 1 / tc $end
$var reg 4 ; count [3:0] $end
$upscope $end
$scope module sec_ten $end
$var wire 1 % clk $end
$var wire 4 < data [3:0] $end
$var wire 1 = enable $end
$var wire 1 ) loadn $end
$var wire 1 & rstn $end
$var wire 1 + zero $end
$var wire 1 . tc $end
$var reg 4 > count [3:0] $end
$upscope $end
$upscope $end
$upscope $end
$enddefinitions $end
#0
$dumpvars
bx >
0=
bx <
bx ;
b0 :
bx 9
bx 8
07
bx 6
bx 5
bx 4
bx 3
bx 2
bx 1
x0
x/
x.
x-
x,
x+
b0 *
1)
0(
b0 '
1&
0%
bx $
bx #
bx "
x!
$end
#10000
b1000 '
b1000 *
b1000 :
#50000
0)
#55000
0!
0.
0,
0/
b1000 2
b1000 ;
b1000 <
1%
#100000
1)
#105000
0%
#200000
b1001 '
b1001 *
b1001 :
#250000
0)
#255000
0+
b1000 1
b1000 8
b1000 >
b1001 2
b1001 ;
b1001 <
1%
#300000
1)
#305000
0%
#400000
b10 '
b10 *
b10 :
#450000
0)
#455000
0-
00
b10 2
b10 ;
b10 <
b1001 1
b1001 8
b1001 >
b1000 3
b1000 9
1%
#500000
1)
#505000
0%
#510000
1!
1.
1-
10
1+
1,
1/
b0 3
b0 9
b0 1
b0 8
b0 >
b0 2
b0 ;
b0 <
0&
#520000
1&
#590000
b1 '
b1 *
b1 :
#630000
0)
#635000
0!
0.
0,
0/
b1 2
b1 ;
b1 <
1%
#680000
1)
#685000
0%
#780000
b10 '
b10 *
b10 :
#830000
0)
#845000
0+
b1 1
b1 8
b1 >
b10 2
b10 ;
b10 <
1%
#880000
1)
#895000
0%
#980000
b0 '
b0 *
b0 :
#1030000
0)
#1045000
1,
1/
0-
00
b0 2
b0 ;
b0 <
b10 1
b10 8
b10 >
b1 3
b1 9
1%
#1080000
1)
#1090000
b0 #
b0 5
b10 "
b10 6
b1 $
b1 4
1=
1(
#1095000
0%
#1105000
b1001 #
b1001 5
b1 "
b1 6
0=
0,
0/
b1 1
b1 8
b1 >
b1001 2
b1001 ;
b1001 <
1%
#1110000
0%
#1115000
b1000 #
b1000 5
b1000 2
b1000 ;
b1000 <
1%
#1120000
0%
#1125000
b111 #
b111 5
b111 2
b111 ;
b111 <
1%
#1130000
0%
#1135000
b110 #
b110 5
b110 2
b110 ;
b110 <
1%
#1140000
0%
#1145000
b101 #
b101 5
b101 2
b101 ;
b101 <
1%
#1150000
0%
#1155000
b100 #
b100 5
b100 2
b100 ;
b100 <
1%
#1160000
0%
#1165000
b11 #
b11 5
b11 2
b11 ;
b11 <
1%
#1170000
0%
#1175000
b10 #
b10 5
b10 2
b10 ;
b10 <
1%
#1180000
0%
#1185000
b1 #
b1 5
b1 2
b1 ;
b1 <
1%
#1190000
0%
#1195000
b0 #
b0 5
1=
1,
1/
b0 2
b0 ;
b0 <
1%
#1200000
0%
#1205000
b1001 #
b1001 5
b0 "
b0 6
0=
1+
0,
0/
b0 1
b0 8
b0 >
b1001 2
b1001 ;
b1001 <
1%
#1210000
0%
#1215000
b1000 #
b1000 5
b1000 2
b1000 ;
b1000 <
1%
#1220000
0%
#1225000
b111 #
b111 5
b111 2
b111 ;
b111 <
1%
#1230000
0%
#1235000
b110 #
b110 5
b110 2
b110 ;
b110 <
1%
#1240000
0%
#1245000
b101 #
b101 5
b101 2
b101 ;
b101 <
1%
#1250000
0%
#1255000
b100 #
b100 5
b100 2
b100 ;
b100 <
1%
#1260000
0%
#1265000
b11 #
b11 5
b11 2
b11 ;
b11 <
1%
#1270000
0%
#1275000
b10 #
b10 5
b10 2
b10 ;
b10 <
1%
#1280000
0%
#1285000
b1 #
b1 5
b1 2
b1 ;
b1 <
1%
#1290000
0%
#1295000
b0 #
b0 5
17
1=
1.
1,
1/
b0 2
b0 ;
b0 <
1%
#1300000
0%
#1305000
b1001 #
b1001 5
b101 "
b101 6
b0 $
b0 4
07
0=
0.
1-
10
0+
0,
0/
b0 3
b0 9
b101 1
b101 8
b101 >
b1001 2
b1001 ;
b1001 <
1%
#1310000
0%
#1315000
b1000 #
b1000 5
b1000 2
b1000 ;
b1000 <
1%
#1320000
0%
#1325000
b111 #
b111 5
b111 2
b111 ;
b111 <
1%
#1330000
0%
#1335000
b110 #
b110 5
b110 2
b110 ;
b110 <
1%
#1340000
0%
#1345000
b101 #
b101 5
b101 2
b101 ;
b101 <
1%
#1350000
0%
#1355000
b100 #
b100 5
b100 2
b100 ;
b100 <
1%
#1360000
0%
#1365000
b11 #
b11 5
b11 2
b11 ;
b11 <
1%
#1370000
0%
#1375000
b10 #
b10 5
b10 2
b10 ;
b10 <
1%
#1380000
0%
#1385000
b1 #
b1 5
b1 2
b1 ;
b1 <
1%
#1390000
0%
#1395000
b0 #
b0 5
1=
1,
1/
b0 2
b0 ;
b0 <
1%
#1400000
0%
#1405000
b1001 #
b1001 5
b100 "
b100 6
0=
0,
0/
b100 1
b100 8
b100 >
b1001 2
b1001 ;
b1001 <
1%
#1410000
0%
#1415000
b1000 #
b1000 5
b1000 2
b1000 ;
b1000 <
1%
#1420000
0%
#1425000
b111 #
b111 5
b111 2
b111 ;
b111 <
1%
#1430000
0%
#1435000
b110 #
b110 5
b110 2
b110 ;
b110 <
1%
#1440000
0%
#1445000
b101 #
b101 5
b101 2
b101 ;
b101 <
1%
#1450000
0%
#1455000
b100 #
b100 5
b100 2
b100 ;
b100 <
1%
#1460000
0%
#1465000
b11 #
b11 5
b11 2
b11 ;
b11 <
1%
#1470000
0%
#1475000
b10 #
b10 5
b10 2
b10 ;
b10 <
1%
#1480000
0%
#1485000
b1 #
b1 5
b1 2
b1 ;
b1 <
1%
#1490000
0%
#1495000
b0 #
b0 5
1=
1,
1/
b0 2
b0 ;
b0 <
1%
#1500000
0%
#1505000
b1001 #
b1001 5
b11 "
b11 6
0=
0,
0/
b11 1
b11 8
b11 >
b1001 2
b1001 ;
b1001 <
1%
#1510000
0%
#1515000
b1000 #
b1000 5
b1000 2
b1000 ;
b1000 <
1%
#1520000
0%
#1525000
b111 #
b111 5
b111 2
b111 ;
b111 <
1%
#1530000
0%
#1535000
b110 #
b110 5
b110 2
b110 ;
b110 <
1%
#1540000
0%
#1545000
b101 #
b101 5
b101 2
b101 ;
b101 <
1%
#1550000
0%
#1555000
b100 #
b100 5
b100 2
b100 ;
b100 <
1%
#1560000
0%
#1565000
b11 #
b11 5
b11 2
b11 ;
b11 <
1%
#1570000
0%
#1575000
b10 #
b10 5
b10 2
b10 ;
b10 <
1%
#1580000
0%
#1585000
b1 #
b1 5
b1 2
b1 ;
b1 <
1%
#1590000
0%
#1595000
b0 #
b0 5
1=
1,
1/
b0 2
b0 ;
b0 <
1%
#1600000
0%
#1605000
b1001 #
b1001 5
b10 "
b10 6
0=
0,
0/
b10 1
b10 8
b10 >
b1001 2
b1001 ;
b1001 <
1%
#1610000
0%
#1615000
b1000 #
b1000 5
b1000 2
b1000 ;
b1000 <
1%
#1620000
0%
#1625000
b111 #
b111 5
b111 2
b111 ;
b111 <
1%
#1630000
0%
#1635000
b110 #
b110 5
b110 2
b110 ;
b110 <
1%
#1640000
0%
#1645000
b101 #
b101 5
b101 2
b101 ;
b101 <
1%
#1650000
0%
#1655000
b100 #
b100 5
b100 2
b100 ;
b100 <
1%
#1660000
0%
#1665000
b11 #
b11 5
b11 2
b11 ;
b11 <
1%
#1670000
0%
#1675000
b10 #
b10 5
b10 2
b10 ;
b10 <
1%
#1680000
0%
#1685000
b1 #
b1 5
b1 2
b1 ;
b1 <
1%
#1690000
0%
#1695000
b0 #
b0 5
1=
1,
1/
b0 2
b0 ;
b0 <
1%
#1700000
0%
#1705000
b1001 #
b1001 5
b1 "
b1 6
0=
0,
0/
b1 1
b1 8
b1 >
b1001 2
b1001 ;
b1001 <
1%
#1710000
0%
#1715000
b1000 #
b1000 5
b1000 2
b1000 ;
b1000 <
1%
#1720000
0%
#1725000
b111 #
b111 5
b111 2
b111 ;
b111 <
1%
#1730000
0%
#1735000
b110 #
b110 5
b110 2
b110 ;
b110 <
1%
#1740000
0%
#1745000
b101 #
b101 5
b101 2
b101 ;
b101 <
1%
#1750000
0%
#1755000
b100 #
b100 5
b100 2
b100 ;
b100 <
1%
#1760000
0%
#1765000
b11 #
b11 5
b11 2
b11 ;
b11 <
1%
#1770000
0%
#1775000
b10 #
b10 5
b10 2
b10 ;
b10 <
1%
#1780000
0%
#1785000
b1 #
b1 5
b1 2
b1 ;
b1 <
1%
#1790000
0%
#1795000
b0 #
b0 5
1=
1,
1/
b0 2
b0 ;
b0 <
1%
#1800000
0%
#1805000
b1001 #
b1001 5
b0 "
b0 6
0=
1+
0,
0/
b0 1
b0 8
b0 >
b1001 2
b1001 ;
b1001 <
1%
#1810000
0%
#1815000
b1000 #
b1000 5
b1000 2
b1000 ;
b1000 <
1%
#1820000
0%
#1825000
b111 #
b111 5
b111 2
b111 ;
b111 <
1%
#1830000
0%
#1835000
b110 #
b110 5
b110 2
b110 ;
b110 <
1%
#1840000
0%
#1845000
b101 #
b101 5
b101 2
b101 ;
b101 <
1%
#1850000
0%
#1855000
b100 #
b100 5
b100 2
b100 ;
b100 <
1%
#1860000
0%
#1865000
b11 #
b11 5
b11 2
b11 ;
b11 <
1%
#1870000
0%
#1875000
b10 #
b10 5
b10 2
b10 ;
b10 <
1%
#1880000
0%
#1885000
b1 #
b1 5
b1 2
b1 ;
b1 <
1%
#1890000
0%
#1895000
b0 #
b0 5
1!
17
1=
1.
1,
1/
b0 2
b0 ;
b0 <
1%
#1900000
bx #
bx 5
bx "
bx 6
bx $
bx 4
0=
07
0(
0%
#6240000
0&
#6290000
1&
